kubeinfra/__init__.py
kubeinfra/cli/__init__.py
kubeinfra/cli/cli.py
kubeinfra/commands/__init__.py
kubeinfra/commands/chat.py
kubeinfra/commands/complete.py
kubeinfra/commands/embeddings.py
kubeinfra/commands/files.py
kubeinfra/commands/finetune.py
kubeinfra/commands/image.py
kubeinfra/commands/models.py
kubeinfra/complete.py
kubeinfra/embeddings.py
kubeinfra/error.py
kubeinfra/files.py
kubeinfra/finetune.py
kubeinfra/image-0.png
kubeinfra/image.py
kubeinfra/models.json
kubeinfra/models.py
kubeinfra/tools/__init__.py
kubeinfra/tools/conversation.py
kubeinfra/types.py
kubeinfra/utils.py
kubeinfra/version.py
kubeinfra-0.0.1a4.dist-info/METADATA
kubeinfra-0.0.1a4.dist-info/WHEEL
kubeinfra-0.0.1a4.dist-info/entry_points.txt
kubeinfra-0.0.1a4.dist-info/RECORD
