Metadata-Version: 2.1
Name: kubeinfra
Version: 0.0.1a4
Summary: 
Author: liuf
Author-email: liuf@kubesphere.io
Requires-Python: >=3.7,<4.0
Classifier: Programming Language :: Python :: 3
Classifier: Programming Language :: Python :: 3.7
Classifier: Programming Language :: Python :: 3.8
Classifier: Programming Language :: Python :: 3.9
Classifier: Programming Language :: Python :: 3.10
Classifier: Programming Language :: Python :: 3.11
Classifier: Programming Language :: Python :: 3.12
Requires-Dist: aiohttp (>=3.9.5,<4.0.0)
Requires-Dist: openai (>=1.28.0,<2.0.0)
Requires-Dist: pydantic (>=2.7.1,<3.0.0)
Requires-Dist: requests (>=2.31.0,<3.0.0)
Requires-Dist: sseclient (>=0.0.27,<0.0.28)
Requires-Dist: tabulate (>=0.9.0,<0.10.0)
